Maxar_Portal_SDK/__init__.py
Maxar_Portal_SDK/interface.py
Maxar_Portal_SDK/process.py
Maxar_Portal_SDK/account_service/__init__.py
Maxar_Portal_SDK/account_service/accounts.py
Maxar_Portal_SDK/account_service/activations.py
Maxar_Portal_SDK/account_service/addresses.py
Maxar_Portal_SDK/account_service/interface.py
Maxar_Portal_SDK/account_service/products.py
Maxar_Portal_SDK/account_service/rate_tables.py
Maxar_Portal_SDK/account_service/roles.py
Maxar_Portal_SDK/account_service/usage.py
Maxar_Portal_SDK/account_service/users.py
Maxar_Portal_SDK/auth/__init__.py
Maxar_Portal_SDK/auth/auth.py
Maxar_Portal_SDK/ogc/__init__.py
Maxar_Portal_SDK/ogc/cli_commands.py
Maxar_Portal_SDK/ogc/interface.py
Maxar_Portal_SDK/ogc/wcs.py
Maxar_Portal_SDK/ogc/wfs.py
Maxar_Portal_SDK/ogc/wms.py
Maxar_Portal_SDK/ogc/wmts.py
Maxar_Portal_SDK/token_service/__init__.py
Maxar_Portal_SDK/token_service/cli_commands.py
Maxar_Portal_SDK/token_service/token.py
Maxar_Portal_SDK-1.1.2.dist-info/METADATA
Maxar_Portal_SDK-1.1.2.dist-info/WHEEL
Maxar_Portal_SDK-1.1.2.dist-info/entry_points.txt
Maxar_Portal_SDK-1.1.2.dist-info/top_level.txt
Maxar_Portal_SDK-1.1.2.dist-info/RECORD
